Metadata-Version: 1.0
Name: xcproxy
Version: 4.2.88
Summary: Xi Ci proxy
Home-page: UNKNOWN
Author: Alex_HuA
Author-email: UNKNOWN
License: MPL-2.0
Keywords: pip,xcproxy,XCproxy,XC,xc
Platform: any
